walkmapper/__init__.py
walkmapper/routes.py
walkmapper/utils.py
walkmapper-0.0.1.dist-info/LICENSE
walkmapper-0.0.1.dist-info/METADATA
walkmapper-0.0.1.dist-info/WHEEL
walkmapper-0.0.1.dist-info/top_level.txt
walkmapper-0.0.1.dist-info/RECORD
