Metadata-Version: 2.1
Name: walkmapper
Version: 0.0.1
Summary: A package for plotting and animating .gpx files
Home-page: https://github.com/sam-olson/walkmapper
Author: Sam Olson
Author-email: solson1014@gmail.com
License: UNKNOWN
Platform: UNKNOWN
Classifier: Programming Language :: Python :: 3
Classifier: License :: OSI Approved :: MIT License
Classifier: Operating System :: OS Independent
Requires-Python: >=3.6
